examples/__init__.py
examples/example.py
examples/run_example.py
tests/__init__.py
tests/test_metrics.py
tests/test_nas.py
zero_cost_search/__init__.py
zero_cost_search/cli.py
zero_cost_search/zero_cost_search.py
zero_cost_search/models/__init__.py
zero_cost_search/models/mlp.py
zero_cost_search/utils/__init__.py
zero_cost_search/utils/export.py
zero_cost_search/utils/logging.py
zero_cost_search/utils/visualization.py
zero_cost_search-0.1.1.dist-info/licenses/LICENSE
zero_cost_search-0.1.1.dist-info/METADATA
zero_cost_search-0.1.1.dist-info/WHEEL
zero_cost_search-0.1.1.dist-info/entry_points.txt
zero_cost_search-0.1.1.dist-info/top_level.txt
zero_cost_search-0.1.1.dist-info/RECORD
